pyfost/gestion_studio/__init__.py
pyfost/gestion_studio/_app.py
pyfost/gestion_studio/_version.py
pyfost/gestion_studio/main_all.py
pyfost/gestion_studio/main_backends.py
pyfost/gestion_studio/main_frontends.py
pyfost/gestion_studio/settings.py
pyfost/gestion_studio/assets/fost_studio_cover.jpeg
pyfost/gestion_studio/assets/fost_studio_logo.ico
pyfost/gestion_studio/assets/fost_studio_logo.jpeg
pyfost/gestion_studio/assets/fost_studio_logo_noborders.jpeg
pyfost/gestion_studio/assets/favicon/android-chrome-192x192.png
pyfost/gestion_studio/assets/favicon/android-chrome-512x512.png
pyfost/gestion_studio/assets/favicon/apple-touch-icon.png
pyfost/gestion_studio/assets/favicon/favicon-16x16.png
pyfost/gestion_studio/assets/favicon/favicon-32x32.png
pyfost/gestion_studio/assets/favicon/favicon.ico
pyfost/gestion_studio/assets/favicon/site.webmanifest
pyfost/gestion_studio/components/__init__.py
pyfost/gestion_studio/components/header.py
pyfost/gestion_studio/components/icon_selector.py
pyfost/gestion_studio/components/link_lists.py
pyfost/gestion_studio/components/theming.py
pyfost/gestion_studio/components/map/generate_svg.py
pyfost/gestion_studio/components/map/isvg.js
pyfost/gestion_studio/components/map/isvg.py
pyfost/gestion_studio/components/map/map.py
pyfost/gestion_studio/components/map/map_TEMPLATE.svg
pyfost/gestion_studio/components/map/map_view.py
pyfost/gestion_studio/components/map/svg_manip/__init__.py
pyfost/gestion_studio/components/map/svg_manip/defs.py
pyfost/gestion_studio/components/map/svg_manip/usages.py
pyfost/gestion_studio/components/zoomable/__init__.py
pyfost/gestion_studio/components/zoomable/zoomable.js
pyfost/gestion_studio/floors/__init__.py
pyfost/gestion_studio/floors/api/__init__.py
pyfost/gestion_studio/floors/api/models.py
pyfost/gestion_studio/floors/backend/__init__.py
pyfost/gestion_studio/floors/backend/database.py
pyfost/gestion_studio/floors/backend/main.py
pyfost/gestion_studio/floors/backend/models.py
pyfost_gestion_studio-0.1.5.dist-info/METADATA
pyfost_gestion_studio-0.1.5.dist-info/WHEEL
pyfost_gestion_studio-0.1.5.dist-info/licenses/LICENSE
pyfost_gestion_studio-0.1.5.dist-info/RECORD
