Metadata-Version: 2.4
Name: pyfost.gestion-studio
Version: 0.1.5
Summary: Studio Seat Management Tools
Project-URL: Documentation, https://github.com/fost-studio/pyfost.gestion-studio#readme
Project-URL: Issues, https://github.com/fost-studio/pyfost.gestion-studio/issues
Project-URL: Source, https://github.com/fost-studio/pyfost.gestion-studio
Author-email: Dee <dee.somethech@gmail.com>
License-Expression: GPL-3.0-or-later
License-File: LICENSE
Classifier: Development Status :: 4 - Beta
Classifier: Programming Language :: Python
Classifier: Programming Language :: Python :: 3.12
Classifier: Programming Language :: Python :: Implementation :: CPython
Classifier: Programming Language :: Python :: Implementation :: PyPy
Requires-Python: >=3.12
Requires-Dist: cssutils
Requires-Dist: drawsvg~=2.0
Requires-Dist: fastapi
Requires-Dist: fastapi[standard]
Requires-Dist: httpx
Requires-Dist: lxml
Requires-Dist: nicegui
Requires-Dist: pydantic
Requires-Dist: pydantic-settings
Requires-Dist: pyfost-adminui
Requires-Dist: python-dotenv
Requires-Dist: python-multipart
Requires-Dist: sqlmodel
Requires-Dist: svgelements
Requires-Dist: svgwrite
